[
  {
    "id": "360ce292-5a0e-81c1-a6af-d06b6cc1d85d",
    "titol": "Festa Major de Parets del Vallès",
    "data": "2024-07-28",
    "tipus": "Diada",
    "descripcio": "Parets del Vallès — Festa Major de Parets del Vallès. Castells: 2xPd4, 4d6a, 3d6a, 4d6, Pd4"
  },
  {
    "id": "360ce292-5a0e-81fd-b18a-d3571e04db40",
    "titol": "Festa Major de Sant Celoni 2024",
    "data": "2024-09-07",
    "tipus": "Diada",
    "descripcio": "Sant Celoni — Festa Major de Sant Celoni. Castells: 2xPd4, 3d6a, 4d6a, id4d6, 4d6, 2xPd4"
  },
  {
    "id": "360ce292-5a0e-8159-9208-c35899607e60",
    "titol": "I Aniversari del Bateig",
    "data": "2024-10-20",
    "tipus": "Diada",
    "descripcio": "Santa Maria de Palautordera — I Aniversari del bateig de la Colla Castellera del Baix Montseny. Castells: 2xPd4, 3d6a, 5d6, 4d6a, 2xPd4"
  },
  {
    "id": "360ce292-5a0e-81e9-a07e-e4717530ac12",
    "titol": "XI Trobada colles Vallès Oriental",
    "data": "2025-06-01",
    "tipus": "Diada",
    "descripcio": "Granollers — XI Trobada de colles del Vallès Oriental. Castells: 2xPd4, 4d6a, 5d6, 3d6a, 2xPd4"
  },
  {
    "id": "360ce292-5a0e-81bb-9ddc-cb249fafdde2",
    "titol": "Festa Major de Sant Jaume — Sant Pol de Mar",
    "data": "2025-07-27",
    "tipus": "Diada",
    "descripcio": "Sant Pol de Mar — Festa Major de Sant Jaume. Castells: idPd4, 4d6, 2d6, 3d6a, Pd4"
  },
  {
    "id": "360ce292-5a0e-8159-b2f1-fc3fccb76b3f",
    "titol": "Festa Major de Sant Celoni 2025",
    "data": "2025-09-06",
    "tipus": "Diada",
    "descripcio": "Sant Celoni — Festa Major de Sant Celoni. Castells: 2xPd4, 4d6, 2d6, 3d6, 2xPd4"
  },
  {
    "id": "360ce292-5a0e-81e0-ac18-fd83eba0b97a",
    "titol": "29a Fira de l'All — Cornellà de Terri",
    "data": "2025-10-05",
    "tipus": "Diada",
    "descripcio": "Cornellà de Terri — 29a Fira de l'All de Cornellà del Terri. Castells: Pd4, 3d6a, 2d6, 3d6, 2xPd4"
  },
  {
    "id": "360ce292-5a0e-81f2-8b23-f35c8f0b69d7",
    "titol": "II Aniversari del Bateig",
    "data": "2025-10-19",
    "tipus": "Diada",
    "descripcio": "Santa Maria de Palautordera — II Aniversari del bateig de la Colla Castellera del Baix Montseny. Castells: 2xPd4, 5d6, 2d6, 4d6a, 2xPd4"
  },
  {
    "id": "360ce292-5a0e-811a-b0c4-d2bc6be52b3e",
    "titol": "Diada de Tardor — Palautordera",
    "data": "2025-11-02",
    "tipus": "Diada",
    "descripcio": "Santa Maria de Palautordera — Diada de Festa de Tardor de la Colla Castellera del Baix Montseny. Castells: 2xPd4, 3d6, 5d6, 4d6, 2xPd4"
  },
  {
    "id": "360ce292-5a0e-81b0-8f65-f007b879fc66",
    "titol": "Diada de Primavera 2026",
    "data": "2026-03-22",
    "tipus": "Diada",
    "descripcio": "Sant Esteve de Palautordera — Diada de primavera de la Colla Castellera del Baix Montseny. Castells: 2xPd4, id3d6a, 5d6, 3d6a, 4d6, 2xPd4"
  }
]